FunctionCreation/ClearDTCMethodFactory.py
FunctionCreation/DiagnosticSessionControlMethodFactory.py
FunctionCreation/ECUResetMethodFactory.py
FunctionCreation/InputOutputControlMethodFactory.py
FunctionCreation/ReadDTCMethodFactory.py
FunctionCreation/ReadDataByIdentifierMethodFactory.py
FunctionCreation/RequestDownloadMethodFactory.py
FunctionCreation/RequestUploadMethodFactory.py
FunctionCreation/RoutineControlMethodFactory.py
FunctionCreation/SecurityAccessMethodFactory.py
FunctionCreation/TesterPresentMethodFactory.py
FunctionCreation/TransferDataMethodFactory.py
FunctionCreation/TransferExitMethodFactory.py
FunctionCreation/WriteDataByIdentifierMethodFactory.py
FunctionCreation/__init__.py
FunctionCreation/iServiceMethodFactory.py
ISOStandard/ISOStandard.py
ISOStandard/__init__.py
SupportedServices/ClearDTCContainer.py
SupportedServices/DiagnosticSessionControlContainer.py
SupportedServices/ECUResetContainer.py
SupportedServices/InputOutputControlContainer.py
SupportedServices/ReadDTCContainer.py
SupportedServices/ReadDataByIdentifierContainer.py
SupportedServices/RequestDownloadContainer.py
SupportedServices/RequestUploadContainer.py
SupportedServices/RoutineControlContainer.py
SupportedServices/SecurityAccessContainer.py
SupportedServices/TesterPresentContainer.py
SupportedServices/TransferDataContainer.py
SupportedServices/TransferExitContainer.py
SupportedServices/WriteDataByIdentifierContainer.py
SupportedServices/__init__.py
SupportedServices/iContainer.py
can_connect/CanConnection.py
can_connect/CanConnectionFactory.py
can_connect/CanTp.py
can_connect/CanTpTypes.py
can_connect/ResettableTimer.py
can_connect/TpFactory.py
can_connect/UtilityFunctions.py
can_connect/__init__.py
can_connect/config.ini
can_connect/iResettableTimer.py
can_connect/iTp.py
uds/Uds.py
uds/__init__.py
uds/config.ini
uds_configuration/Config.py
uds_configuration/__init__.py
uds_configuration/defaultConfig.ini
uds_connect/__init__.py
uds_connect/uds_connect.py
uds_connect-1.0.dist-info/LICENSE
uds_connect-1.0.dist-info/METADATA
uds_connect-1.0.dist-info/WHEEL
uds_connect-1.0.dist-info/top_level.txt
uds_connect-1.0.dist-info/RECORD
