Metadata-Version: 2.1
Name: uds_connect
Version: 1.0
Summary: A package to interface with UDS via different CAN interfaces
Home-page: https://github.com/ojrane16124/uds_connect
Author: Omkar Rane
Author-email: ojrane16124@gmail.com
License: MIT
Classifier: Programming Language :: Python :: 3
Classifier: License :: OSI Approved :: MIT License
Classifier: Operating System :: OS Independent
Requires-Python: >=3.6
License-File: LICENSE
Requires-Dist: uds
Requires-Dist: python-can
